Workbook

Sheet Gastos e acompanhamentos
A1: Gastos e acompanhamento 2019
B5: Janeiro | C5: fevereiro | D5: março | E5: abril | F5: maio | G5: junho | H5: julho | I5: agosto | J5: setembro | K5: outubro | L5: novembro | M5: dezembro
A6: Renda 1 | B6: =943.69+164.85+152.64 -> 1261.18 | C6: =943.69+144.1+150 -> 1237.79 | D6: =943.69+144.1 -> 1087.79 | E6: =1297.14+943.69+49+10 -> 2299.83 | F6: =E27+144+144+150+3292.86+411.5 -> 5738.115 | G6: =4925.315+24.5+4255.36 -> 9205.175 | H6: =7173.68+34+24+76.55+1025 -> 8333.23 | I6: =6769.97+75.82+175+200+1025+150 -> 8395.79 | J6: =I26-22.29+100+1025+998+150 -> 9561.575 | K6: =8237.53+1025+68.85+100 -> 9431.38 | L6: =K26+16.96+1025 -> 8804.22 | M6: 7257.92
A7: Renda 2 | E7: 100 | F7: ='Gastos Maio'!L113 -> 34 | J7: 200 | K7: 179
A8: Tesouro
A9: Poupança
A10: Total | B10: =SUM(B6:B9) -> 1261.18 | C10: =SUM(C6:C9) -> 1237.79 | D10: =SUM(D6:D9) -> 1087.79 | E10: =SUM(E6:E9) -> 2399.83 | F10: =SUM(F6:F9) -> 5772.115 | G10: =SUM(G6:G9) -> 9205.175 | H10: =SUM(H6:H9) -> 8333.23 | I10: =SUM(I6:I9) -> 8395.79 | ... M10: =SUM(M6:M9) -> 7257.92
A12: Despesas | B12: Janeiro | C12: fevereiro | D12: março | E12: abril | F12: maio | G12: junho | H12: julho | I12: agosto | J12: setembro | K12: outubro | L12: novembro | M12: dezembro
A13: Celular | B13: ='Gastos Janeiro'!L76 -> 0 | C13: ='Gastos Fevereiro'!L62 -> 62 | D13: ='Gastos Março'!L65 -> 50 | E13: ='Gastos Abril'!L66 -> 50 | F13: ='Gastos Maio'!L69 -> 50 | G13: ='Gastos Junho'!L76 -> 50 | H13: ='Gastos Julho'!L74 -> 50 | I13: ='Gastos Agosto'!L75 -> 51 | J13: ='Gastos Setembro'!L75 -> 50 | K13: ='Gastos Outubro'!L75 -> 50 | L13: ='Gastos Novembro'!L75 -> 54.99 | M13: ='Gastos Dezembro'!L75 -> 0
A14: Luz | B14: ='Gastos Janeiro'!L87 -> 0 | C14: ='Gastos Fevereiro'!L73 -> 45.0675 | D14: ='Gastos Março'!L76 -> 49.306667 | E14: ='Gastos Abril'!L77 -> 90.315 | F14: ='Gastos Maio'!L80 -> 0 | G14: ='Gastos Junho'!L87 -> 172.33 | H14: ='Gastos Julho'!L85 -> 227.87 | I14: ='Gastos Agosto'!L86 -> 154.25 | J14: ='Gastos Setembro'!L86 -> 121.69667 | K14: ='Gastos Outubro'!L86 -> 189.58 | L14: ='Gastos Novembro'!L86 -> 43.5 | M14: ='Gastos Dezembro'!L86 -> 52.39
A15: Água | B15: ='Gastos Janeiro'!F87 -> 0 | C15: ='Gastos Fevereiro'!F73 -> 6.135 | D15: ='Gastos Março'!F76 -> 8.1333333 | E15: ='Gastos Abril'!F77 -> 12.98 | F15: ='Gastos Maio'!F80 -> 0 | G15: ='Gastos Junho'!F87 -> 37.94 | H15: ='Gastos Julho'!F85 -> 3 | I15: ='Gastos Agosto'!F86 -> 19.89 | J15: ='Gastos Setembro'!F86 -> 27.903333 | K15: ='Gastos Outubro'!F86 -> 43.82 | L15: ='Gastos Novembro'!F86 -> 43.5 | M15: ='Gastos Dezembro'!F86 -> 24.9
A16: Gás | B16: ='Gastos Janeiro'!F98 -> 0 | C16: ='Gastos Fevereiro'!F84 -> 0 | D16: ='Gastos Março'!F87 -> 0 | E16: ='Gastos Abril'!F88 -> 0 | F16: ='Gastos Maio'!F113 -> 0 | G16: ='Gastos Junho'!F120 -> 0 | H16: ='Gastos Julho'!F118 -> 0 | I16: ='Gastos Agosto'!F119 -> 0 | J16: ='Gastos Setembro'!F119 -> 0 | K16: ='Gastos Outubro'!F119 -> 0 | L16: ='Gastos Novembro'!F119 -> 0 | M16: ='Gastos Dezembro'!F119 -> 36
A17: Entretenimento | B17: ='Gastos Janeiro'!F40 -> 29 | C17: ='Gastos Fevereiro'!F27 -> 0 | D17: ='Gastos Março'!F31 -> 25 | E17: ='Gastos Abril'!F24 -> 7 | F17: ='Gastos Maio'!F36 -> 0 | G17: ='Gastos Junho'!F36 -> 0 | H17: ='Gastos Julho'!F36 -> 0 | I17: ='Gastos Agosto'!F37 -> 30.725 | J17: ='Gastos Setembro'!F37 -> 0 | K17: ='Gastos Outubro'!F37 -> 0 | L17: ='Gastos Novembro'!F37 -> 7 | M17: ='Gastos Dezembro'!F37 -> 0
A18: Sherlock | B18: ='Gastos Janeiro'!F76 -> 10 | C18: ='Gastos Fevereiro'!F62 -> 20 | D18: ='Gastos Março'!F65 -> 20 | E18: ='Gastos Abril'!F66 -> 20 | F18: ='Gastos Maio'!F69 -> 0 | G18: ='Gastos Junho'!F76 -> 20 | H18: ='Gastos Julho'!F74 -> 30 | I18: ='Gastos Agosto'!F75 -> 20 | J18: ='Gastos Setembro'!F75 -> 20 | K18: ='Gastos Outubro'!F75 -> 14.87 | L18: ='Gastos Novembro'!F75 -> 0 | M18: ='Gastos Dezembro'!F75 -> 20
A19: Compras casa | B19: ='Gastos Janeiro'!L65 -> 120.76 | C19: ='Gastos Fevereiro'!L51 -> 124 | D19: ='Gastos Março'!L54 -> 179.4 | E19: ='Gastos Abril'!L55 -> 237.63 | F19: ='Gastos Maio'!L58 -> 211.52 | G19: ='Gastos Junho'!L65 -> 165.61 | H19: ='Gastos Julho'!L63 -> 60.52 | I19: ='Gastos Agosto'!L64 -> 124.47 | J19: ='Gastos Setembro'!L64 -> 116.33 | K19: ='Gastos Outubro'!L64 -> 87.64 | L19: ='Gastos Novembro'!L64 -> 53.57 | M19: ='Gastos Dezembro'!L64 -> 62.61
A20: Pessoal | B20: ='Gastos Janeiro'!F65 -> 941.27 | C20: ='Gastos Fevereiro'!F51 -> 1381.24 | D20: ='Gastos Março'!F54 -> 1074.04 | E20: ='Gastos Abril'!F55 -> 490.71 | F20: ='Gastos Maio'!F58 -> 605.74 | G20: ='Gastos Junho'!F65 -> 989.37 | H20: ='Gastos Julho'!F63 -> 1013.93 | I20: ='Gastos Agosto'!F64 -> 352.65 | J20: ='Gastos Setembro'!F64 -> 860.7 | K20: ='Gastos Outubro'!F64 -> 1263.04 | L20: ='Gastos Novembro'!F64 -> 1283.515 | M20: ='Gastos Dezembro'!F64 -> 357.11
A21: Comida | B21: ='Gastos Janeiro'!L40 -> 113.253 | C21: ='Gastos Fevereiro'!L27 -> 81.32 | D21: ='Gastos Março'!L31 -> 113.92 | E21: ='Gastos Abril'!L24 -> 113.75 | F21: ='Gastos Maio'!L36 -> 105.69 | G21: ='Gastos Junho'!L36 -> 91.26 | H21: ='Gastos Julho'!L36 -> 94.39 | I21: ='Gastos Agosto'!L37 -> 79.25 | J21: ='Gastos Setembro'!L37 -> 41.25 | K21: ='Gastos Outubro'!L37 -> 53.66 | L21: ='Gastos Novembro'!L37 -> 31.79 | M21: ='Gastos Dezembro'!L37 -> 88.5
A22: Moto | B22: ='Gastos Janeiro'!F109 -> 154.9 | C22: ='Gastos Fevereiro'!F95 -> 124.72 | D22: ='Gastos Março'!F98 -> 195.22 | E22: ='Gastos Abril'!F99 -> 170.24 | F22: ='Gastos Maio'!F127 -> 178 | G22: ='Gastos Junho'!F131 -> 406.57 | H22: ='Gastos Julho'!F129 -> 40 | I22: ='Gastos Agosto'!F139 -> 137 | J22: ='Gastos Setembro'!F139 -> 115.04 | K22: ='Gastos Outubro'!F139 -> 145.51 | L22: ='Gastos Novembro'!F139 -> 159.63 | M22: ='Gastos Dezembro'!F139 -> 105
A23: Total | B23: =SUM(B13:B22) -> 1369.183 | C23: =SUM(C13:C22) -> 1844.4825 | D23: =SUM(D13:D22) -> 1715.02 | E23: =SUM(E13:E22) -> 1192.625 | F23: =SUM(F13:F22) -> 1150.95 | G23: =SUM(G13:G22) -> 1933.08 | H23: =SUM(H13:H22)+48.39 -> 1568.1 | I23: =SUM(I13:I22)+61.23 -> 1030.465 | J23: =SUM(J13:J22)+45.99+125.14 -> 1524.05 | K23: =SUM(K13:K22) -> 1848.12 | L23: =SUM(L13:L22) -> 1677.495 | M23: =SUM(M13:M22) -> 746.51
B25: Janeiro | C25: fevereiro | D25: março | E25: abril | F25: maio | G25: junho | H25: julho | I25: agosto | J25: setembro | K25: outubro | L25: novembro | M25: dezembro
A26: Saldo | B26: =B10-B23 -> -108.003 | C26: =C10-C23 -> -606.6925 | D26: =D10-D23 -> -627.23 | E26: =E10-E23 -> 1207.205 | F26: =F6-F23+60 -> 4647.165 | G26: =G10-G23+5.93 -> 7278.025 | H26: =H10-H23+4.84 -> 6769.97 | I26: =I10-I23-54.46 -> 7310.865 | J26: =J10-J23 -> 8237.525 | K26: =K10-K23 -> 7762.26 | L26: =L10-L23 -> 7126.725 | M26: =M10-M23 -> 6511.41
A27: Total | B27: =589.54+B26+124.63+2.3 -> 608.467 | C27: 701.3 | D27: =D26+C27+26.15+239.51+203.84 -> 543.57 | E27: =E26+D27-155.02 -> 1595.755 | F27: =F26+291.54-13.39 -> 4925.315 | G27: =G26-70.34 -> 7207.685 | N27: =M14+L14+K14+J14+I14+H14+G14 -> 961.61667
A28: Meta de gastos | C28: 350 | E28: 1500 | F28: 774.09 | G28: 1500 | I28: =850-I23 -> -180.465 | J28: =800-J23 -> -724.05 | N28: =N27/7 -> 137.37381
G29: =G28-G23 -> -433.08 | N29: =M15+L15+K15+J15+I15+H15+G15 -> 200.95333
A30: 10% entretenimento | J30: =800*0.1 -> 80 | N30: =N29/7 -> 28.707619
N31: =N28+N30 -> 166.08143
G39: 3115.18
G40: =G39+4058.5 -> 7173.68

Sheet Gastos Janeiro
B1: JANEIRO
B4: Entretenimento | H4: Comida
B5: Observação | E5: dia | F5: R$ | H5: Observação | K5: dia | L5: R$
B6: ingresso WI-FI RALPH | E6: 43470 | F6: 7 | H6: leite casa da Bia | K6: 43466 | L6: 3.4
B7: Giovana parque de diversões | E7: 43471 | F7: 15 | H7: pão | K7: 43467 | L7: 2
B8: cinema dragon ball super broly | E8: 43479 | F8: 7 | H8: lanche da tarde | K8: 43467 | L8: 3
H9: bis para o pessoal | K9: 43467 | L9: 3.99
H10: pão | K10: 43468 | L10: 1.5
H11: lanche cinema | K11: 43470 | L11: 14.47
H12: janta | K12: 43470 | L12: 6
H13: lanche | K13: 43471 | L13: 8.9
H14: pão | K14: 43472 | L14: 2
H15: pão | K15: 43474 | L15: 2
H16: pão | K16: 43475 | L16: 1.5
H17: janta | K17: 43475 | L17: 3
H18: pão | K18: 43476 | L18: 1.5
H19: pão | K19: 43477 | L19: 0.5
H20: café da manhã | K20: 43478 | L20: =4+0.5 -> 4.5
H21: lanche cinema | K21: 43478 | L21: 15.7
H22: pão | K22: 43480 | L22: 1.5
H23: lanche manhã | K23: 43481 | L23: 4.44
H24: pão | K24: 43482 | L24: 1.5
H25: pão | K25: 43483 | L25: 1.5
H26: batatinha | K26: 43483 | L26: 2
H27: janta | K27: 43484 | L27: 5.15
H28: pão | K28: 43121 | L28: 2
H29: pão e lanche | K29: 43122 | L29: =1.5+3+0.7 -> 5.2
H30: café da manhã + suco | K30: 43123 | L30: =1.5+2 -> 3.5
H31: pão | K31: 43124 | L31: 1.503
H32: pão | K32: 43490 | L32: 1.5
H33: pão | K33: 43493 | L33: 1.5
H34: pão | K34: 43494 | L34: 1.5
H35: pão + lanche | K35: 43495 | L35: =1.5 +3 -> 4.5
H36: pão | K36: 43496 | L36: 2
B40: Total | F40: =SUM(F6:F12) -> 29 | H40: Total | L40: =SUM(L6:L39) -> 113.253
B42: Pessoal | H42: Compras casa
B43: Observação | E43: dia | F43: R$ | H43: Observação | K43: dia | L43: R$
H44: banana | K44: 43473 | L44: 2.44
B45: Caderno para as coisas do comercial | E45: 43467 | F45: 8.69 | H45: churrasco mãe | K45: 43475 | L45: 3 | M45: =L47+L50+L52+L55+L61 -> 18.39
B46: remedio e camisinha | E46: 43469 | F46: 16 | H46: almoço | K46: 43477 | L46: 6 | M46: =L46+L49+L59 -> 19.5
B47: netflix | E47: 43470 | F47: 19 | H47: leite | K47: 43476 | L47: 4 | M47: =L48+L57+L62 -> 44
B48: sapatos | E48: 43471 | F48: 109.98 | H48: janta pizza | K48: 43477 | L48: 14
H49: almoço | K49: 43113 | L49: 8
B50: trufas | E50: 43473 | F50: 100 | H50: leite | K50: 43479 | L50: 4
B51: adaptador para headset | E51: 43473 | F51: 25.9 | H51: diferença amaciante | K51: 43482 | L51: 2
B52: adaptador para headset - diferença | E52: 43474 | F52: 24 | H52: leite | K52: 43482 | L52: 2.39
B53: livro copywriting kindle | E53: 43475 | F53: 7 | H53: cafe,bolacha,goiaba,farofa | K53: 43486 | L53: 12.12
B54: spotfy | E54: 43112 | F54: 5 | H54: açucar | K54: 43489 | L54: 2.6
B55: caderno para anotações | E55: 43113 | F55: 3.8 | H55: leite | K55: 43490 | L55: 4
B56: Colégio da Giovana | E56: 43479 | F56: 250 | H56: leite+caixa de fosforo | K56: 43493 | L56: =6.7-1.5 -> 5.2
B57: Tripé para o celular | E57: 43481 | F57: 25 | H57: pizza | K57: 43491 | L57: =15+(15-8) -> 22
B58: trufas | E58: 43483 | F58: 70 | H58: lanche com a bia | K58: 43491 | L58: 5.03
B59: ferro de solda e solda | E59: 43484 | F59: =19.9+9 -> 28.9 | H59: almoço (linguiça + ovo) | K59: 43492 | L59: 5.5
B60: internet | E60: 43487 | F60: 24 | H60: café e açúcar | K60: 43494 | L60: 6.48
B61: emprestimo mãe | E61: 43488 | F61: 150 | H61: leite | K61: 43495 | L61: 4
B62: trufas | E62: 43492 | F62: 70 | H62: jantar | K62: 43496 | L62: 8
B63: camisinha | E63: 43492 | F63: 4
B65: Total | F65: =SUM(F44:F64) -> 941.27 | L65: =SUM(L44:L64) -> 120.76
B67: Sherlock | H67: Celular
B68: Observação | E68: dia | F68: R$ | H68: Observação | K68: dia | L68: R$
B69: ração | E69: 43496 | F69: 10
B76: Total | F76: =SUM(F69:F75) -> 10 | H76: Total | L76: =SUM(L69:L75) -> 0
B78: Água | H78: Luz
B79: Observação | E79: dia | F79: R$ | H79: Observação | K79: dia | L79: R$
B87: Total | F87: =SUM(F80:F86) -> 0 | H87: Total | L87: =SUM(L80:L86) -> 0
B89: Gás | H89: Renda trufas
B90: Observação | E90: dia | F90: R$ | H90: Observação | K90: dia | L90: R$
B98: Total | F98: =SUM(F91:F97) -> 0 | H98: Total | L98: =SUM(L91:L97) -> 0
B100: Moto
B101: Observação | E101: dia | F101: R$
B102: seguro DPVAT | E102: 43102 | F102: 84.58
B103: estacionamento (grand shopping) | E103: 43470 | F103: 1.5
B104: gasolina | E104: 43470 | F104: 35.02
B105: estacionamento (grand shopping) | E105: 43478 | F105: 1.5
B106: estacionamento (via sul) | E106: 43472 | F106: 2.3
B107: gasolina | E107: 43483 | F107: 20
B108: gasolina | E108: 43494 | F108: 10
B109: Total | F109: =SUM(F102:F108) -> 154.9

Sheet Gastos Fevereiro
B1: FEVEREIRO
B4: Entretenimento | H4: Comida
B5: Observação | E5: dia | F5: R$ | H5: Observação | K5: dia | L5: R$
H6: pão | K6: 43497 | L6: 1
H7: café da manhã + pão da tarde | K7: 43498 | L7: 5.25
H8: pão | K8: 43499 | L8: 0.5
H9: pão | K9: 43500 | L9: 2
H10: lanche com a Bia | K10: 43499 | L10: 6
H11: PÃO | K11: 43501 | L11: 1.5
H12: pão | K12: 43502 | L12: 1.5
H13: pão | K13: 43503 | L13: 1.5
H14: pão | K14: 43504 | L14: 1.5
H15: lanche com a Bia | K15: 43505 | L15: 5.5
H16: pão | K16: 43506 | L16: 2
H17: pão mãe | K17: 43511 | L17: 1
... H23: Pão | K23: 43521 | L23: 2
H24: pão + lanche + lanche faculdade | K24: 43522 | L24: =1.5+4.5+2.5 -> 8.5
H25: pão + leite | K25: 43523 | L25: 5
H26: pão + biscoito | K26: 43524 | L26: 3.5
B27: Total | F27: =SUM(F6:F12) -> 0 | H27: Total | L27: =SUM(L6:L26) -> 81.32
B29: Pessoal | H29: Compras casa
B30: Observação | E30: dia | F30: R$ | H30: Observação | K30: dia | L30: R$
B31: desodorante | E31: 43498 | F31: 10.99 | H31: leite + café | K31: 43503 | L31: 7.18
B32: meias | E32: 43499 | F32: 20 | H32: almoço linguiça | K32: 43505 | L32: 4
B33: capa de chuva + mel | E33: 43502 | F33: =100+8.95 -> 108.95 | H33: almoço | K33: 43506 | L33: 15
B34: trufas + perfume | E34: 43503 | F34: =85+70 -> 155 | H34: venish e omo | K34: 43506 | L34: 12.98
B35: jogo kingdom hearts 3 | E35: 43506 | F35: 300 | H35: leite | K35: 43508 | L35: 3.19
B36: trufa | E36: 43508 | F36: 80 | H36: pão de forma + queijo e presunto | K36: 43509 | L36: 13
B37: coca cola | E37: 43508 | F37: 3 | H37: jantar com a Bia | K37: 43511 | L37: 11.5
B38: spotfy | E38: 43508 | F38: 5 | H38: açucar, farinha d'água | K38: 43512 | L38: 5.75
B39: reforço Giovana | E39: 43511 | F39: 120 | H39: esfirras | K39: 43512 | L39: 7.5
B40: remédio de verme | E40: 43511 | F40: 25 | H40: janta pastel | K40: 43515 | L40: 6
B41: corte de cabelo | E41: 43510 | F41: 13 | H41: janta mais pão e requeijão | K41: 43516 | L41: 20.4
B42: trufas | E42: 43513 | F42: 80 | H42: pizza casa | K42: 43520 | L42: 10
B43: remedios | E43: 43514 | F43: 25 | H43: leite | K43: 43521 | L43: 4
B44: Sapato + camiseta | E44: 43517 | F44: =79.9+19.9 -> 99.8 | H44: leite | K44: 43518 | L44: 3.5
B45: conserto do ziper da mochila | E45: 43519 | F45: 10
B46: camisinha | E46: 43518 | F46: 5.5
B47: Cabelo da mãe + emprestimo (R$ 125,00) | E47: 43519 | F47: =125+80 -> 205
B48: trufas | E48: 43521 | F48: 60
B49: luftal | E49: 43521 | F49: 8
B50: internet | E50: 43521 | F50: =70-23 -> 47
B51: Total | F51: =SUM(F31:F50) -> 1381.24 | L51: =SUM(L31:L50) -> 124
B53: Sherlock | H53: Celular
B54: Observação | E54: dia | F54: R$ | H54: Observação | K54: dia | L54: R$
B55: ração | E55: 43504 | F55: 20 | H55: crédito | K55: 43497 | L55: 12
H56: plano de chamadas e de internet | K56: 43510 | L56: 50
B62: Total | F62: =SUM(F55:F61) -> 20 | H62: Total | L62: =SUM(L55:L61) -> 62
B64: Água | H64: Luz
B65: Observação | E65: dia | F65: R$ | H65: Observação | K65: dia | L65: R$
B66: agua | E66: 43504 | F66: =24.54/4 -> 6.135 | H66: enel | K66: 43505 | L66: =180.27/4 -> 45.0675
B73: Total | F73: =SUM(F66:F72) -> 6.135 | H73: Total | L73: =SUM(L66:L72) -> 45.0675
B75: Gás | H75: Renda trufas
B76: Observação | E76: dia | F76: R$ | H76: Observação | K76: dia | L76: R$
B84: Total | F84: =SUM(F77:F83) -> 0 | H84: Total | L84: =SUM(L77:L83) -> 0
B86: Moto
B87: Observação | E87: dia | F87: R$
B88: gasolina | E88: 43498 | F88: 20
B89: gasolina moto | E89: 43505 | F89: 38.22
B90: estacionamento grand shopping | E90: 43505 | F90: 1.5
B91: troca de óleo | E91: 43515 | F91: 22
B92: gasolina | E92: 43517 | F92: 10 | H92: =F88+F89+F92+F94 -> 88.22
B93: freio + pisca (manutenção) | E93: 43519 | F93: 13
B94: gasolina | E94: 43522 | F94: 20
B95: Total | F95: =SUM(F88:F94) -> 124.72

Sheet Gastos Março
B1: MARÇO
B4: Entretenimento | H4: Comida
B5: Observação | E5: dia | F5: R$ | H5: Observação | K5: dia | L5: R$
B6: hipergame | E6: 43529 | F6: 13 | H6: Pão | K6: 43525 | L6: 1.5
B7: Cinema Capitã Marvel | E7: 43542 | F7: 12 | H7: jantar pizza | K7: 43526 | L7: 15
H8: pão | K8: 43527 | L8: 1.5
H9: tarde com a bia | K9: 43529 | L9: 12
H10: pão + lanche | K10: 43530 | L10: =1.5+1 -> 2.5
H11: pão+lanche | K11: 43531 | L11: =1.5+2 -> 3.5
H12: pão | K12: 43532 | L12: 1.5
H13: almoço | K13: 43533 | L13: 4
H14: pão | K14: 43535 | L14: 2
H15: pão+lanche | K15: 43536 | L15: =1.5+2 -> 3.5
H16: pão | K16: 43537 | L16: 2
H17: pão | K17: 43538 | L17: 1.5
H18: pão+lanche | K18: 43539 | L18: =1.5+1 -> 2.5
H19: pão | K19: 43540 | L19: 0.5
H20: lanche cinema | K20: 43541 | L20: 12.02
H21: pão | K21: 43542 | L21: 2
H22: pão | K22: 43543 | L22: 2
H23: pão+leite+lanche | K23: 43544 | L23: 6.6
H24: pão | K24: 43546 | L24: 6
H25: pão | K25: 43548 | L25: 1.5
H26: pão+almoço de aniversário da D. Vania | K26: 43550 | L26: =2+12.05 -> 14.05
H27: pão + lanche da faculdade | K27: 43551 | L27: 8
H28: tapioca | K28: 43552 | L28: 2
H29: pão | K29: 43554 | L29: 2
H30: pão+lanche de tarde | K30: 43555 | L30: =2+2.25 -> 4.25
B31: Total | F31: =SUM(F6:F12) -> 25 | H31: Total | L31: =SUM(L6:L30) -> 113.92
B33: Pessoal | H33: Compras casa
B34: Observação | E34: dia | F34: R$ | H34: Observação | K34: dia | L34: R$
B35: gilete | E35: 43528 | F35: 4.49 | H35: Leite | K35: 43525 | L35: 3.5
B36: trufas | E36: 43529 | F36: 70 | H36: compras | K36: 43527 | L36: 17.85
B37: play 4 | E37: 43532 | F37: 200 | H37: leite | K37: 43528 | L37: =2.79*2 -> 5.58
B38: trufas | E38: 43534 | F38: 88 | H38: bolo + manteiga + farinha dágua | K38: 43528 | L38: =6.19+3+5.99 -> 15.18
B39: camisinha | E39: 43541 | F39: 2.99 | H39: amendoim | K39: 43529 | L39: 2.5
B40: trufas | E40: 43541 | F40: 82.5 | H40: café + açucar | K40: 43530 | L40: 6.28
B41: Concerto de celular para venda | E41: 43541 | F41: 120 | H41: almoço | K41: 43534 | L41: 21.9
B42: niver De Vania | E42: 43544 | F42: 20 | H42: ovo+pilha+tang | K42: 43534 | L42: =19.44+1.2 -> 20.64
B43: emprestar ao Paulo | E43: 43545 | F43: 20 | H43: leite | K43: 43539 | L43: 3.5
B44: internet | E44: 43544 | F44: =69.9/3 -> 23.3 | H44: ovo+farinha | K44: 43540 | L44: 14.99
B45: pão + lanche faculdade colocar no tipo certo | E45: 43545 | F45: =1.5+2 -> 3.5 | H45: venish + amaciante | K45: 43541 | L45: =8.19+2.79 -> 10.98
H46: bolacha | K46: 43547 | L46: 2
B47: Limpar meu nome IBI CARD | E47: 43545 | F47: 357.76 | H47: leite | K47: 43548 | L47: 4
B48: camisa | E48: 43548 | F48: 1.5 | H48: sabão + frango | K48: 43548 | L48: 13
B49: emprestar ao Paulo | E49: 43553 | F49: 20 | H49: leite | K49: 43549 | L49: 3
B50: concerto | E50: 43554 | F50: 60 | H50: café | K50: 43550 | L50: 5
H51: leite | K51: 43552 | L51: 3.5
H52: linguiça | K52: 43552 | L52: 5
H53: pizza | K53: 43555 | L53: 21
B54: Total | F54: =SUM(F35:F52) -> 1074.04 | L54: =SUM(L35:L53) -> 179.4
B56: Sherlock | H56: Celular
B57: Observação | E57: dia | F57: R$ | H57: Observação | K57: dia | L57: R$
B58: ração | E58: 43530 | F58: 20 | H58: crédito celular | K58: 43538 | L58: 50
B65: Total | F65: =SUM(F58:F64) -> 20 | H65: Total | L65: =SUM(L58:L64) -> 50
B67: Água | H67: Luz
B68: Observação | E68: dia | F68: R$ | H68: Observação | K68: dia | L68: R$
B69: cagece | E69: 43535 | F69: =24.4/3 -> 8.1333333 | H69: enel | K69: 43535 | L69: =147.92/3 -> 49.306667
B76: Total | F76: =SUM(F69:F75) -> 8.1333333 | H76: Total | L76: =SUM(L69:L75) -> 49.306667
B78: Gás | H78: Renda trufas
B79: Observação | E79: dia | F79: R$ | H79: Observação | K79: dia | L79: R$
B87: Total | F87: =SUM(F80:F86) -> 0 | H87: Total | L87: =SUM(L80:L86) -> 0
B89: Moto
B90: Observação | E90: dia | F90: R$
B91: gasolina | E91: 43526 | F91: 42.55
B92: gasolina | E92: 43535 | F92: 40.67
B93: carcaça frontal, 2 redentor + serviço | E93: 43540 | F93: 72
B94: gasolina | E94: 43545 | F94: 20
B95: gasolina | E95: 43549 | F95: 20
B98: Total | F98: =SUM(F91:F97) -> 195.22

Sheet Gastos Abril
B1: Abril
B4: Entretenimento | H4: Comida
B5: Observação | E5: dia | F5: R$ | H5: Observação | K5: dia | L5: R$
B6: ingresso SHAZAM | E6: 43562 | F6: 7 | H6: pão | K6: 43558 | L6: 1
H7: yakult | K7: 43558 | L7: 2.58
H8: pão | K8: 43559 | L8: 1
H9: pão | K9: 43560 | L9: 1
H10: lanche cinema | K10: 43562 | L10: 34.44 | M10: =L6+L8+L9+L11+L12+L13+L14+L15+L16+L17+L18+L19+L20+L21+L22 -> 62.9
H11: pão | K11: 43564 | L11: 1
H12: pão | K12: 43565 | L12: 1
H13: salgado + balas | K13: 43565 | L13: =3.5+0.4 -> 3.9
H14: lanche + agua+ pão da tarde | K14: 43566 | L14: =4+2+1.5 -> 7.5
H15: Almoço | K15: 43566 | L15: 10
H16: pão | K16: 43571 | L16: 1
H17: pao | K17: 43579 | L17: 2
H18: pão | K18: 43580 | L18: 1
H19: pizza+ tampico + agua | K19: 43580 | L19: 14
H20: almoço | K20: 43581 | L20: 16
H21: pão | K21: 43581 | L21: 1.5
H22: pão | K22: 43582 | L22: 1
H23: lanche cinema | K23: 43583 | L23: 13.83
B24: Total | F24: =SUM(F6:F12) -> 7 | H24: Total | L24: =SUM(L6:L23) -> 113.75
B26: Pessoal | H26: Compras casa
B27: Observação | E27: dia | F27: R$ | H27: Observação | K27: dia | L27: R$
B28: 3º parcela | E28: 43559 | F28: 200 | H28: frango | K28: 43556 | L28: 8
B29: camisinha | E29: 43560 | F29: 3.5 | H29: agua | K29: 43556 | L29: 8
B30: Caderno | E30: 43561 | F30: 13 | H30: churrasco | K30: 43557 | L30: 7
B31: estacionamento | E31: 43562 | F31: 2.6 | H31: ovo | K31: 43558 | L31: 12.49
B32: diferença da Bia | E32: 43563 | F32: 2.4 | H32: pizzas aniversário do gean | K32: 43560 | L32: 30.8
B33: shampo anticaspa | E33: 43564 | F33: 15.04 | H33: leite | K33: 43560 | L33: 2.69
B34: Camisas | E34: 43566 | F34: =45+25 -> 70 | H34: fardo de leite | K34: 43561 | L34: 30.36
B35: passagem para o centro fashion | E35: 43566 | F35: 1.6 | H35: inseticida + feijão verde | K35: 43563 | L35: =9.49+3.39 -> 12.88
B36: desodorante+2antimofo | E36: 43573 | F36: =10.99+2.09+2.09 -> 15.17 | H36: Danone Giovana | K36: 43564 | L36: 2.39
B37: emprestar a mae | E37: 43573 | F37: 50 | H37: almoço | K37: 43568 | L37: 19.9
B38: presente bia | E38: 43574 | F38: 24 | H38: bolo, iogurte, chamyto | K38: 43569 | L38: 11.36
B39: camisinha | E39: 43574 | F39: 4.5 | H39: almoço | K39: 43569 | L39: 5.67
B40: ingressos cinema | E40: 43576 | F40: 23 | H40: gás | K40: 43569 | L40: =23.33 -> 23.33
B41: internet | E41: 43577 | F41: =70-23.33 -> 46.67 | H41: caixa de ovos | K41: 43538 | L41: 10
B42: corte de cabelo | E42: 43578 | F42: 13 | H42: amaciante+farinha | K42: 43571 | L42: =2.79+3 -> 5.79
B43: cheetos + chamyto | E43: 43579 | F43: =1.75+1.98 -> 3.73 | H43: Banana+Gioaba | K43: 43573 | L43: =1.52+3.01 -> 4.53
B44: estacionamento via sul | E44: 43583 | F44: 2.5 | H44: caixa de ovos | K44: 43574 | L44: 12.5
H45: venish | K45: 43575 | L45: 10.45
H46: banana + ninho + cheetos + sucos | K46: 43576 | L46: =21.5+3.7-17.5 -> 7.7
H47: Almoço frango | K47: 43578 | L47: 1
H48: café | K48: 43579 | L48: 4.2
H49: leite | K49: 43580 | L49: 2.59
H50: Garrafão | K50: 43581 | L50: 4
B55: Total | F55: =SUM(F28:F46) -> 490.71 | L55: =SUM(L28:L54) -> 237.63
B57: Sherlock | H57: Celular
B58: Observação | E58: dia | F58: R$ | H58: Observação | K58: dia | L58: R$
B59: ração | E59: 43564 | F59: 20 | H59: crédito | K59: 43571 | L59: 50
B66: Total | F66: =SUM(F59:F65) -> 20 | H66: Total | L66: =SUM(L59:L65) -> 50
B68: Água | H68: Luz
B69: Observação | E69: dia | F69: R$ | H69: Observação | K69: dia | L69: R$
B70: agua | E70: 43565 | F70: =25.96/4+6.49 -> 12.98 | H70: energia | K70: 43565 | L70: =180.62/4+45.16 -> 90.315
B77: Total | F77: =SUM(F70:F76) -> 12.98 | H77: Total | L77: =SUM(L70:L76) -> 90.315
B79: Gás | H79: Renda trufas
B80: Observação | E80: dia | F80: R$ | H80: Observação | K80: dia | L80: R$
B88: Total | F88: =SUM(F81:F87) -> 0 | H88: Total | L88: =SUM(L81:L87) -> 0
B90: Moto
B91: Observação | E91: dia | F91: R$
B92: gasolina | E92: 43556 | F92: 43.24
B93: manutenção | E93: 43558 | F93: 85
B94: troca e óleo | E94: 43564 | F94: 22
B95: gasolina | E95: 43583 | F95: 20
B99: Total | F99: =SUM(F92:F98) -> 170.24

Sheet Gastos Maio
B1: Maio
B4: Entretenimento | H4: Comida
B5: Observação | E5: dia | F5: R$ | H5: Observação | K5: dia | L5: R$
H6: pão + lanche faculdade+janta | K6: 43587 | L6: =1+1.2+3 -> 5.2
H7: pão+lanche | K7: 43588 | L7: =1+2.7 -> 3.7
H8: água | K8: 43589 | L8: 1
H9: caixa de leite | K9: 43589 | L9: 3.5
H10: rufles | K10: 43589 | L10: 11.78
H11: pastel de queijo | K11: 43590 | L11: 6
H12: pão + tortuguita | K12: 43591 | L12: 3
H13: pão + Tortuguita | K13: 43592 | L13: =1.5+1 -> 2.5
H14: pão | K14: 43593 | L14: 1 | M14: =L6+L7+L9+L12+L13+L14+L15+L16+L18+L20+L21+L22+L23+L24+L25+L26+L27+L29+L30+L31 -> 58.61
H15: pão+lanche | K15: 43594 | L15: =1+1.1 -> 2.1
H16: pão | K16: 43596 | L16: 1.5
H17: sorvete+2chetos e uma coca cola | K17: 43597 | L17: =6+2 -> 8
H18: Pão+lanche | K18: 43598 | L18: =1+4.28 -> 5.28
H19: pastel de queijo+suco | K19: 43597 | L19: 7.8
H20: pão+lanche | K20: 43599 | L20: =1+1 -> 2
H21: pão+tortuguita | K21: 43601 | L21: =1+1 -> 2
H22: pão de côco | K22: 43603 | L22: 3
H23: Tortuguita | K23: 43605 | L23: 1
H24: tortuguita | K24: 43606 | L24: 1
H25: delicitos + churrasco | K25: 43607 | L25: 5
H26: pão+tortuguita+churrasco | K26: 43608 | L26: 5
H27: pão+maçã+biscoito | K27: 43609 | L27: =1+2.33+3 -> 6.33
H28: pizza | K28: 43609 | L28: 10
H29: pão | K29: 43610 | L29: 3
H30: pão | K30: 43613 | L30: 1.5
H31: pão | K31: 43614 | L31: 1
H32: batatinha | K32: 43616 | L32: 2.5
B36: Total | F36: =SUM(F6:F12) -> 0 | H36: Total | L36: =SUM(L6:L35) -> 105.69
B38: Pessoal | H38: Compras casa
B39: Observação | E39: dia | F39: R$ | H39: Observação | K39: dia | L39: R$
B40: dar dinheiro a mãe | E40: 43586 | F40: 5 | H40: reforço da giovana | K40: 43586 | L40: 60
B41: capacete | E41: 43589 | F41: 64 | H41: caixa de ovos | K41: 43588 | L41: 10
B42: cuecas | E42: 43589 | F42: 20 | H42: agua sanitaria,amaciante, sabao em pó,vanish | K42: 43589 | L42: =3.08+2.59+8.99+3.89 -> 18.55
B43: dinheiro do flanelinha | E43: 43589 | F43: 0.75 | H43: bolacha cream cracker | K43: 43590 | L43: 3.69
B44: trufas | E44: 43590 | F44: 82.5 | H44: biscoito da giovana | K44: 43593 | L44: 1.8
B45: Divida com o gean quitada (play 4 + kh collection) | E45: 43590 | F45: 32.24 | H45: café santa clara | K45: 43594 | L45: 2.5
B46: Netflix | E46: 43590 | F46: 19 | H46: energia mais agua (para separar depois) | K46: 43595 | L46: 61
B47: trufas | E47: 43595 | F47: 93.5 | H47: pizza | K47: 43595 | L47: 10
B48: cinema detetive pikachu Nort shopping ant. bezerra | E48: 43597 | F48: 12 | H48: café santa clara | K48: 43598 | L48: 5.5
B49: estacionamento ( paguei estacionamento de carro) | E49: 43597 | F49: 7 | H49: baiao + frango | K49: 43603 | L49: 16
B50: Fralda para o chá revelação para Kamylla | E50: 43599 | F50: 14 | H50: mortadela | K50: 43610 | L50: 2.79
B51: dar dinheiro pro JV | E51: 43602 | F51: 0.6 | H51: sabão brilhante | K51: 43612 | L51: 7.69
B52: Camisinha + teste de gravidez | E52: 43602 | F52: 13 | H52: caixa de ovos | K52: 43615 | L52: 12
B53: trufas | E53: 43604 | F53: 77
B54: pokemon idiota | E54: 43609 | F54: 2
B55: internet | E55: 43614 | F55: 73.5 | M55: =F55/3 -> 24.5
B56: Reforço Giovana | E56: 43614 | F56: 60 | M56: =M55+26.25 -> 50.75
B57: coisas para fazer Brigadeiro | E57: 43616 | F57: 29.65
B58: Total | F58: =SUM(F40:F57) -> 605.74 | L58: =SUM(L40:L54) -> 211.52
B60: Sherlock | H60: Celular
B61: Observação | E61: dia | F61: R$ | H61: Observação | K61: dia | L61: R$
H62: Crédito celular | K62: 43602 | L62: 50
B69: Total | F69: =SUM(F62:F68) -> 0 | H69: Total | L69: =SUM(L62:L68) -> 50
B71: Água | H71: Luz
B72: Observação | E72: dia | F72: R$ | H72: Observação | K72: dia | L72: R$
B80: Total | F80: =SUM(F73:F79) -> 0 | H80: Total | L80: =SUM(L73:L79) -> 0
B82: Gás | H82: Renda 2 - Trufas
B83: Observação | E83: dia | F83: R$ | H83: Observação | K83: dia | L83: R$
H84: bia comprou 2 trufas | K84: 43590 | L84: 4
H85: vendas | K85: 43591 | L85: 30
B113: Total | F113: =SUM(F84:F90) -> 0 | H113: Total | L113: =SUM(L84:L112) -> 34
B115: Moto
B116: Observação | E116: dia | F116: R$
B117: gasolina | E117: 43587 | F117: 10
B118: gasolina | E118: 43589 | F118: 20
B119: gasolina | E119: 43593 | F119: 20
B120: troca de óleo | E120: 43595 | F120: 18
B121: gasolina | E121: 43597 | F121: 20
B122: gasolina | E122: 43600 | F122: 20
B123: gasolina | E123: 43605 | F123: 20
B124: gasolina | E124: 43608 | F124: 10
B125: gasolina | E125: 43611 | F125: 20
B126: gasolina | E126: 43615 | F126: 20
B127: Total | F127: =SUM(F117:F126) -> 178

Sheet Gastos Junho
B1: Junho
B4: Entretenimento | H4: Comida
B5: Observação | E5: dia | F5: R$ | H5: Observação | K5: dia | L5: R$
H6: salgado + água | K6: 43619 | L6: 5.5
H7: tortuguita+icekiss | K7: 43711 | L7: 1.3
H8: sorvete | K8: 43622 | L8: 2
H9: pão | K9: 43624 | L9: 2
H10: lanche para o filme John Wick 3 | K10: 43624 | L10: 13.97
H11: pão | K11: 43625 | L11: 2
H12: pão | K12: 43626 | L12: 2
H13: pão | K13: 43628 | L13: 1.5
H14: batom garoto | K14: 43627 | L14: 1.5
H15: pão | K15: 43628 | L15: 0.5
H16: pão | K16: 43629 | L16: 1
H17: comida para viagem para guaramiranga | K17: 43630 | L17: =12.3+6.2 -> 18.5
H18: pão | K18: 43633 | L18: 1.5
H19: pão | K19: 43634 | L19: 1.5
H20: pão | K20: 43635 | L20: 1.5
H21: pão | K21: 43636 | L21: 1.5
H22: pão | K22: 43640 | L22: 1.5
H23: jantar pizza com a Bia | K23: 43640 | L23: 5
H24: pão | K24: 43641 | L24: 1
H25: pão | K25: 43642 | L25: 2
H26: lanche para o filme toy story | K26: 43642 | L26: =9+1.5+4 -> 14.5
H27: caixa e ovo | K27: 43643 | L27: 7.99
H28: pão | K28: 43644 | L28: 1.5
B36: Total | F36: =SUM(F6:F12) -> 0 | H36: Total | L36: =SUM(L6:L35) -> 91.26
B38: Pessoal | H38: Compras casa
B39: Observação | E39: dia | F39: R$ | H39: Observação | K39: dia | L39: R$
B40: predinisolona | E40: 43618 | F40: 13 | H40: pastel da giovana | K40: 43619 | L40: 2
B41: concerto da calça | E41: 43619 | F41: 2 | H41: Banana+Farinha dágua | K41: 43623 | L41: 5.01
B42: corte de cabelo | E42: 43620 | F42: 10 | H42: garrafão 2x | K42: 43624 | L42: 8
B43: 3 anti-mofo | E43: 43621 | F43: 7.47 | H43: leite 2x | K43: 43624 | L43: 7.18
B44: Fonte 500 W | E44: 43621 | F44: 150 | H44: leite | K44: 43626 | L44: 3.5
B45: dar dinheiro a mãe | E45: 43623 | F45: 2 | H45: frango + cheiro verde | K45: 43627 | L45: 8.5
B46: estacionamento via sul | E46: 43623 | F46: 2.3 | H46: banana | K46: 43628 | L46: 3.18
B47: Livro - O pequeno principe | E47: 43623 | F47: 10 | H47: din Din mãe | K47: 43628 | L47: 1
B48: netflix | E48: 43621 | F48: 23 | H48: leite | K48: 43633 | L48: 3.59
B49: ingresso - John Wick 3 | E49: 43624 | F49: 14 | H49: café + cream cracker | K49: 43633 | L49: 7.68
B50: estacionamento via sul | E50: 43624 | F50: 2.6 | H50: leite | K50: 43635 | L50: 3.39
B51: perfume kaik comprei da mãe | E51: não lembro | F51: 100 | H51: leite | K51: 43637 | L51: 3.49
B52: xerox documentos | E52: 43626 | F52: 1.6 | H52: garrafão 2x | K52: 43635 | L52: 6
B53: estacionamento messejana | E53: 43627 | F53: 5 | H53: leite | K53: 43640 | L53: 4
B54: placa mae entrada | E54: 43628 | F54: 150 | H54: sabão líquido | K54: 43640 | L54: 7.69
B55: placa mae restante | E55: 43629 | F55: 200 | H55: coca-cola | K55: 43639 | L55: 2
B56: viagem guaramiranga (passagens+aluguel+barraca+café da manhã+ janta) | E56: 43634 | F56: 131.21 | H56: internet | K56: 43640 | L56: 72.31
B57: prestobarba | E57: 43636 | F57: 4.89 | H57: leite + qualy | K57: 43642 | L57: =3.59+1 -> 4.59
B58: emprestar dinheiro a Bia | E58: 43639 | F58: 50 | H58: leite | K58: 43644 | L58: 3.5
B59: estacionamento grand shopping | E59: 43639 | F59: 4 | H59: bolo+sabonete | K59: 43646 | L59: 9
B60: estacionamento via sul | E60: 43642 | F60: 2.3
B61: ingresso - toy story 4 | E61: 43642 | F61: 14
B62: reforço da Giovana | E62: 43643 | F62: 60
B63: divida cartão de memória | E63: 43643 | F63: 10
B64: sapatos da mãe (divida cartão de memória) | E64: 43644 | F64: 20
B65: Total | F65: =SUM(F40:F64) -> 989.37 | L65: =SUM(L40:L62) -> 165.61
B67: Sherlock | H67: Celular
B68: Observação | E68: dia | F68: R$ | H68: Observação | K68: dia | L68: R$
B69: ração | E69: 43626 | F69: 20 | H69: crédito | K69: 43632 | L69: 50
B76: Total | F76: =SUM(F69:F75) -> 20 | H76: Total | L76: =SUM(L69:L75) -> 50
B78: Água | H78: Luz
B79: Observação | E79: dia | F79: R$ | H79: Observação | K79: dia | L79: R$
B80: cagece | E80: 43626 | F80: 37.94 | H80: enel | K80: 43626 | L80: 172.33
M82: =L80+F80 -> 210.27
M83: =M82/4 -> 52.5675
B87: Total | F87: =SUM(F80:F86) -> 37.94 | H87: Total | L87: =SUM(L80:L86) -> 172.33
B89: Gás | H89: Renda 2 - Trufas
B90: Observação | E90: dia | F90: R$ | H90: Observação | K90: dia | L90: R$
B91: Gás | E91: 43640 | F91: 70
B120: Total | F120: =SUM(F93:F97) -> 0 | H120: Total | L120: =SUM(L91:L119) -> 0
B122: Moto
B123: Observação | E123: dia | F123: R$
B124: troca de óleo | E124: 43620 | F124: 15
B125: gasolina | E125: 43621 | F125: 10
B126: revisão | E126: 43622 | F126: 300
B127: gasolina | E127: 43622 | F127: 41.57
B128: gasolina | E128: 43630 | F128: 20
B129: gasolina | E129: 43640 | F129: 20
B131: Total | F131: =SUM(F124:F130) -> 406.57

Sheet Gastos Julho
B1: Julho
B4: Entretenimento | H4: Comida
B5: Observação | E5: dia | F5: R$ | H5: Observação | K5: dia | L5: R$
H6: pão | K6: 43648 | L6: 1
H7: pão | K7: 43649 | L7: 1
H8: pão | K8: 43650 | L8: 1
H9: pão | K9: 43651 | L9: 1
H10: pão | K10: 43653 | L10: 1.5
H11: janta pizza + refri | K11: 43652 | L11: 20
H12: pão | K12: 43654 | L12: 1.5
H13: jantar esfirra | K13: 43654 | L13: 10.4
H14: pão | K14: 43655 | L14: 1.5
H15: lanche cinema | K15: 43654 | L15: 17.5
H16: pão | K16: 43656 | L16: 1.5
H17: pão | K17: 43657 | L17: 1
... H26: chamyto | K26: 43666 | L26: 1.5
H27: janta esfirra | K27: 43666 | L27: =13.4/2 -> 6.7
H28: pão | K28: 43675 | L28: 1.5
H29: pão | K29: 43676 | L29: 1.5
H30: pão | K30: 43675 | L30: 1.5
H31: pão | K31: 43677 | L31: 1.5
H32: pão | K32: 43677 | L32: 1
B36: Total | F36: =SUM(F6:F12) -> 0 | H36: Total | L36: =SUM(L6:L35) -> 94.39
B38: Pessoal | H38: Compras casa
B39: Observação | E39: dia | F39: R$ | H39: Observação | K39: dia | L39: R$
B40: emprestar dinheiro para o paulo | E40: 43647 | F40: 50 | H40: farinha d'agua + arroz | K40: 43648 | L40: =3.59+2.59 -> 6.18
B41: impressão da folha da AF | E41: 43649 | F41: 2 | H41: leite | K41: 43651 | L41: 3.5
B42: passagem para pegar a moto do gean | E42: 43650 | F42: 3.4 | H42: almoço(frango) | K42: 43651 | L42: 4
B43: camisinha | E43: 43651 | F43: 3 | H43: almoço 2x sardinhas | K43: 43651 | L43: 6.38
B44: pack bordelands | E44: 43651 | F44: 11.05 | H44: detergente | K44: 43652 | L44: 1.59
B45: camisinha | E45: 43653 | F45: 5.19 | H45: leite + café | K45: 43653 | L45: 7.5
B46: ingresso Homem-aranha longe de casa | E46: 43655 | F46: 15.5 | H46: ovos | K46: 43656 | L46: 8
B47: memória RAM | E47: 43657 | F47: 140 | H47: farinha d'água + cream cracker | K47: 43660 | L47: =7.38-3 -> 4.38
B48: pasta térmica | E48: 43657 | F48: 15 | H48: leite | K48: 43664 | L48: 3.49
B49: HD +COOLER | E49: 43658 | F49: 150 | H49: manteiga | K49: 43675 | L49: 6
B50: prestobarba+camisinha+sabonete | E50: 43658 | F50: 9.86 | H50: agua sanitaria | K50: 43676 | L50: 6
B51: ida a praia | E51: 43660 | F51: 10.5 | H51: leite | K51: 43677 | L51: 3.5
B52: IPVA do Gean | E52: 43664 | F52: 174.83
B53: emplacamento gean | E53: 43664 | F53: 150
B54: shampoo + condicionador | E54: 43666 | F54: 30.78
B55: ingresso circo | E55: 43666 | F55: 10
B56: entrada do concerto do celular | E56: 43675 | F56: 100
B57: internet | E57: 43675 | F57: =73.64/2 -> 36.82
B58: resto do concerto do celular | E58: 43676 | F58: 50
B59: netflix julho e agosto | E59: 43677 | F59: 46
B63: Total | F63: =SUM(F40:F62) -> 1013.93 | L63: =SUM(L40:L54) -> 60.52
B65: Sherlock | H65: Celular
B66: Observação | E66: dia | F66: R$ | H66: Observação | K66: dia | L66: R$
B67: ração | E67: 43651 | F67: 20 | H67: crédito celular | K67: 43664 | L67: 50
B68: ração | E68: 43675 | F68: 10
B74: Total | F74: =SUM(F67:F73) -> 30 | H74: Total | L74: =SUM(L67:L73) -> 50
B76: Água | H76: Luz
B77: Observação | E77: dia | F77: R$ | H77: Observação | K77: dia | L77: R$
B78: garrafão | E78: 43656 | F78: 3 | H78: enel | K78: 43656 | L78: =139-62.6 -> 76.4
H79: enel | K79: 43677 | L79: =227.47-76 -> 151.47 | M79: =227.47/3 -> 75.823333
M80: =M79+51.03 -> 126.85333
M81: =M80-100 -> 26.853333
B85: Total | F85: =SUM(F78:F84) -> 3 | H85: Total | L85: =SUM(L78:L84) -> 227.87
B87: Gás | H87: Renda 2 - Trufas
B88: Observação | E88: dia | F88: R$ | H88: Observação | K88: dia | L88: R$
B118: Total | F118: =SUM(F89:F95) -> 0 | H118: Total | L118: =SUM(L89:L117) -> 0
B120: Moto
B121: Observação | E121: dia | F121: R$
B122: gasolina | E122: 43648 | F122: 10
B123: gasolina | E123: 43665 | F123: 10
B124: gasolina | E124: 43676 | F124: 20
B129: Total | F129: =SUM(F122:F128) -> 40

Sheet Gastos Agosto
B1: Agosto
B4: Entretenimento | H4: Comida
B5: Observação | E5: dia | F5: R$ | H5: Observação | K5: dia | L5: R$
B6: cinema + comida | E6: 43692 | F6: =(43/2)+(18.45/2) -> 30.725 | H6: pão | K6: 43678 | L6: 1
H7: pão | K7: 43679 | L7: 1
H8: pão | K8: 43681 | L8: 3.5
H9: jantar com a Bia | K9: 43681 | L9: 10.4
H10: pão | K10: 43682 | L10: 3.5
H11: pão | K11: 43683 | L11: 1.5
H12: pão | K12: 43684 | L12: 2
H13: pão | K13: 43685 | L13: 2
H14: pão | K14: 43686 | L14: 3
H15: pão | K15: 43690 | L15: 1
H16: chocolate | K16: 43689 | L16: 1
H17: pão | K17: 43691 | L17: 1.5
H18: pão | K18: 43692 | L18: 2
... H21: churrasco | K21: 43693 | L21: 3
H22: esfirra | K22: 43695 | L22: =(13.4/2)+2.6 -> 9.3
H23: pão | K23: 43696 | L23: 1.5
H24: pão | K24: 43697 | L24: 1.5
H25: pão | K25: 43698 | L25: 1.5
H26: pão | K26: 43700 | L26: 1.5
H27: pão | K27: 43701 | L27: 1.5
H28: lanche da noite com a bia | K28: 43702 | L28: 15.05
H29: pão | K29: 43702 | L29: 1.5
H30: pão | K30: 43704 | L30: 1.5
H31: pão | K31: 43706 | L31: 1.5
H32: chocolate | K32: 43707 | L32: 2
B37: Total | F37: =SUM(F6:F12) -> 30.725 | H37: Total | L37: =SUM(L6:L36) -> 79.25
B39: Pessoal | H39: Compras casa
B40: Observação | E40: dia | F40: R$ | H40: Observação | K40: dia | L40: R$
B41: internet mãe | E41: 43680 | F41: 51.03 | H41: leite + cream cracker | K41: 43678 | L41: 6.68
B42: remedio para dor de cabeça | E42: 43682 | F42: 1 | H42: café principal | K42: 43678 | L42: 3.84
B43: corrente | E43: 43686 | F43: 40 | H43: garrafão | K43: 43678 | L43: 4
B44: repetidor de sinal | E44: 43688 | F44: 40 | H44: 5x ovo | K44: 43682 | L44: 2.5
B45: teclado | F45: 25 | H45: frango | K45: 43683 | L45: 9.9
B46: camisinha | E46: 43693 | F46: 4 | H46: cx de ovo | K46: 43684 | L46: 9
B47: prednisona | E47: 43694 | F47: 12 | H47: garrafão | K47: 43686 | L47: 4
B48: corte de cabelo | E48: 43694 | F48: 13 | H48: leite | K48: 43690 | L48: 3.5
B49: internet | E49: 43697 | F49: =70-32 -> 38 | H49: leite | K49: 15/08/0219 | L49: 3.5
B50: estacionamento centro de eventos | E50: 43702 | F50: 5 | H50: garrafão | K50: 43691 | L50: 4
B51: contas mãe | E51: 43703 | F51: =183.62-150 -> 33.62 | H51: leite | K51: 43697 | L51: 3.5
B52: caixa de som para p pc | E52: 43705 | F52: 25 | H52: leite | K52: 43698 | L52: 3.5
B53: reforço giovana | E53: 43708 | F53: 65 | H53: qualy | K53: 43698 | L53: 5.99
H54: tapioca + bolo + papel higienico | K54: 43698 | L54: 14.27
H55: farinha | K55: 43699 | L55: 3
H56: leite | K56: 43700 | L56: 3.5
H57: frango | K57: 43701 | L57: 10.6
H58: café | K58: 43702 | L58: 4
H59: leite+ovos | K59: 43703 | L59: =9+3.5 -> 12.5
H60: leite+farinha | K60: 43705 | L60: =3.5+2.99 -> 6.49
H61: arroz | K61: 43706 | L61: 2.7
H62: leite | K62: 43707 | L62: 3.5
B64: Total | F64: =SUM(F41:F63) -> 352.65 | L64: =SUM(L41:L63) -> 124.47
B66: Sherlock | H66: Celular
B67: Observação | E67: dia | F67: R$ | H67: Observação | K67: dia | L67: R$
B68: ração | E68: 43684 | F68: 20 | H68: crédito | K68: 43693 | L68: 51
B75: Total | F75: =SUM(F68:F74) -> 20 | H75: Total | L75: =SUM(L68:L74) -> 51
B77: Água | H77: Luz
B78: Observação | E78: dia | F78: R$ | H78: Observação | K78: dia | L78: R$
B79: água | E79: 43686 | F79: =29.84-9.95 -> 19.89 | H79: enel | K79: 43686 | L79: =231.38-77.13 -> 154.25
B86: Total | F86: =SUM(F79:F85) -> 19.89 | H86: Total | L86: =SUM(L79:L85) -> 154.25
B88: Gás | H88: Renda 2 - Trufas
B89: Observação | E89: dia | F89: R$ | H89: Observação | K89: dia | L89: R$
B119: Total | F119: =SUM(F90:F96) -> 0 | H119: Total | L119: =SUM(L90:L118) -> 0
B121: Moto
B122: Observação | E122: dia | F122: R$
B123: troca de óleo | E123: 43685 | F123: 22
B124: gasolina | E124: 43693 | F124: 20
B125: gasolina | E125: 43698 | F125: 40
B126: concerto do velocimetro | E126: 43705 | F126: 35
B127: gasolina | E127: 43707 | F127: 10
B128: gasolina | E128: 43706 | F128: 10
B139: Total | F139: =SUM(F123:F138) -> 137

Sheet Gastos Setembro
B1: Setembro
B4: Entretenimento | H4: Comida
B5: Observação | E5: dia | F5: R$ | H5: Observação | K5: dia | L5: R$
H6: pão | K6: 43497 | L6: 1.5
H7: chocolate | K7: 43712 | L7: 1
H8: lanche | K8: 43713 | L8: 5
H9: pão | K9: 43714 | L9: 1.5
H10: pizza+refri | K10: 43715 | L10: =22.5/2 -> 11.25
H11: pão | K11: 43716 | L11: 1.5
H12: pão | K12: 43718 | L12: 1
H13: pão | K13: 43720 | L13: 1.5
H14: biscoito | K14: 43719 | L14: 2.5
H15: pão | K15: 43726 | L15: 1.5
H16: salgado | K16: 43726 | L16: 3.5
H17: pão | K17: 43727 | L17: 2
H18: pão | K18: 43735 | L18: 2
H19: risole de carne | K19: 43736 | L19: 5.5
B37: Total | F37: =SUM(F6:F12) -> 0 | H37: Total | L37: =SUM(L6:L36) -> 41.25
B39: Pessoal | H39: Compras casa
B40: Observação | E40: dia | F40: R$ | H40: Observação | K40: dia | L40: R$
B41: emprestar dinheiro pro pai | E41: 43709 | F41: 100 | H41: linguiça | K41: 43711 | L41: 6.89
B42: emprestar dinheiro para mãe | E42: 43713 | F42: =269-150 -> 119 | H42: frango | K42: 43718 | L42: 16.75
B43: meu presente de aniversário para mim :) | E43: 43716 | F43: 290 | H43: garrafão | K43: 43718 | L43: 4
B44: emprestar dinheiro a mãe | E44: 43719 | F44: 105 | H44: alho roxo | K44: 43720
B45: adaptador bluetooth para pc | E45: 43720 | F45: 15 | H45: garrafão | K45: 43723 | L45: 8
B46: dinheiro para levar o guarda roupa da mãe | E46: 43720 | F46: 10 | H46: frango | K46: 43726 | L46: 11.4
B47: estacionamento benfica | E47: 43723 | F47: 3.2 | H47: nescau+goiaba+banana | K47: 43727 | L47: 17.63
B48: ingresso eu e Bia | E48: 43723 | F48: =9.5+19 -> 28.5 | H48: bolachas | K48: 43727 | L48: 7.18
B49: internet | E49: 43724 | F49: 60 | H49: 2x leite | K49: 43728 | L49: 6.98
B50: gasolina viagem | E50: 43736 | F50: 20 | H50: frango | K50: 43732 | L50: =15.65-10 -> 5.65
B51: gasolina viagem | E51: 43737 | F51: 10 | H51: 2x leite | K51: 43732 | L51: 6.98
B52: credito psn store | E52: 43737 | F52: 100 | H52: banana + batata | K52: 43733 | L52: 8.9
H53: ovos | K53: 43734 | L53: 8.99
H54: 2x leite | K54: 43737 | L54: 6.98
B64: Total | F64: =SUM(F41:F63) -> 860.7 | L64: =SUM(L41:L55) -> 116.33
B66: Sherlock | H66: Celular
B67: Observação | E67: dia | F67: R$ | H67: Observação | K67: dia | L67: R$
B68: ração | E68: 43715 | F68: 20 | H68: crédito | K68: 43721 | L68: 50
B75: Total | F75: =SUM(F68:F74) -> 20 | H75: Total | L75: =SUM(L68:L74) -> 50
B77: Água | H77: Luz
B78: Observação | E78: dia | F78: R$ | H78: Observação | K78: dia | L78: R$
B79: cagece | E79: 43713 | F79: =(41.86/3)+13.95 -> 27.903333 | H79: enel | K79: 43713 | L79: =(182.54/3)+60.85 -> 121.69667
B86: Total | F86: =SUM(F79:F85) -> 27.903333 | H86: Total | L86: =SUM(L79:L85) -> 121.69667
B88: Gás | H88: Renda 2 - Trufas
B89: Observação | E89: dia | F89: R$ | H89: Observação | K89: dia | L89: R$
B119: Total | F119: =SUM(F90:F96) -> 0 | H119: Total | L119: =SUM(L90:L118) -> 0
B121: Moto
B122: Observação | E122: dia | F122: R$
B123: gasolina | E123: 43711 | F123: 43.04
B124: troca de óleo | E124: 43720 | F124: 22
B125: gasolina | E125: 43720 | F125: 10
B126: gasolina | E126: 43723 | F126: 20
B127: gasolina | E127: 43729 | F127: 20
B139: Total | F139: =SUM(F123:F138) -> 115.04

Sheet Gastos Outubro
B1: Outubro
B4: Entretenimento | H4: Comida
B5: Observação | E5: dia | F5: R$ | H5: Observação | K5: dia | L5: R$
H6: cheetos | K6: 43745 | L6: 2
H7: pão | K7: 43746 | L7: 1.5
H8: pão | K8: 43752 | L8: 1.5
H9: subway com a bia | K9: 43752 | L9: 10
H10: pão | K10: 43753 | L10: 1.5
H11: pão | K11: 43754 | L11: 1.5
H12: 2xcheetos+doritos+nescau | K12: 43756 | L12: =2.19+4.59+2.19+1.19 -> 10.16
H13: pão | K13: 43759 | L13: 1.5
H14: 2x pastel + suco | K14: 43758 | L14: 9
H15: jantar com bia (esfirra+refrigernte) | K15: 43765 | L15: 10
H16: pão | K16: 43766 | L16: 2
H17: pão | K17: 43767 | L17: 1.5
H18: pão | K18: 43769 | L18: 1.5
B37: Total | F37: =SUM(F6:F12) -> 0 | H37: Total | L37: =SUM(L6:L36) -> 53.66
B39: Pessoal | H39: Compras casa
B40: Observação | E40: dia | F40: R$ | H40: Observação | K40: dia | L40: R$
B41: reforço giovana | E41: 43740 | F41: 60 | H41: frango | K41: 43741 | L41: 8
B42: deposito superdigital | E42: 43741 | F42: 100 | H42: almoço | K42: 43751 | L42: 20.9
B43: taxa de licenciamento e expedição de CRLV/CRV | E43: 43741 | F43: 127.82 | H43: queijo presunto pão | K43: 43750 | L43: 17.86
B44: IPVA | E44: 43741 | F44: 91.55 | H44: ovo | K44: 43756 | L44: 10.99
B45: pagamento da porra do cheque especial | E45: 43741 | F45: 11.27 | H45: banana+sardinha | K45: 43760 | L45: 10.89
B46: estacionamento grandshopping | E46: 43741 | F46: 2 | H46: 2x leite | K46: 43764 | L46: =2.89*2 -> 5.78
B47: adaptador pra antena pra vó | E47: 43741 | F47: 1 | H47: batata | K47: 43764 | L47: 4.93
B48: jump force | E48: 43741 | F48: 50 | H48: leite | K48: 43767 | L48: 3.29
B49: netflix (Setembro Outubro) | E49: 43742 | F49: 46 | H49: lanche | K49: 43768 | L49: 5
B50: itapark + comida | E50: 43744 | F50: 31
B51: cinema (coringa)+comida | E51: 43744 | F51: =(42/2)+10 -> 31
B52: matricula muay thai | E52: 43746 | F52: 89
B53: camisinha | E53: 43749 | F53: 7.4
B54: teste de gravidez | E54: 43750 | F54: 10
B55: cabo HDMI | E55: 43752 | F55: 10
B56: dentista | E56: 43752 | F56: 120
B57: internet | E57: 43755 | F57: 60
B58: credito cartão super | E58: 43755 | F58: 400
B59: cortar cabelo | E59: 43767 | F59: 15
B64: Total | F64: =SUM(F41:F63) -> 1263.04 | L64: =SUM(L41:L55) -> 87.64
B66: Sherlock | H66: Celular
B67: Observação | E67: dia | F67: R$ | H67: Observação | K67: dia | L67: R$
B68: ração | E68: 43764 | F68: 4.87 | H68: crédito | K68: 43755 | L68: 50
B69: ração | E69: 43767 | F69: 10
B75: Total | F75: =SUM(F68:F74) -> 14.87 | H75: Total | L75: =SUM(L68:L74) -> 50
B77: Água | H77: Luz
B78: Observação | E78: dia | F78: R$ | H78: Observação | K78: dia | L78: R$
B79: água | E79: 43741 | F79: 43.82 | H79: enel | K79: 43741 | L79: 189.58
M80: =L79+F79 -> 233.4
M84: =(F79+L79)/3 -> 77.8
B86: Total | F86: =SUM(F79:F85) -> 43.82 | H86: Total | L86: =SUM(L79:L85) -> 189.58
B88: Gás | H88: Renda 2 - Trufas
B89: Observação | E89: dia | F89: R$ | H89: Observação | K89: dia | L89: R$
B119: Total | F119: =SUM(F90:F96) -> 0 | H119: Total | L119: =SUM(L90:L118) -> 0
B121: Moto
B122: Observação | E122: dia | F122: R$
B123: gasolina | E123: 43748 | F123: 43.01
B124: troca de óleo | E124: 43749 | F124: 22
B125: gasolina | E125: 43756 | F125: 40
B126: gasolina | E126: 43768 | F126: 40.5
B139: Total | F139: =SUM(F123:F138) -> 145.51

Sheet Gastos Novembro
B1: Novembro
B4: Entretenimento | H4: Comida
B5: Observação | E5: dia | F5: R$ | H5: Observação | K5: dia | L5: R$
B6: ingresso Os parças 2 | E6: 43786 | F6: 7 | H6: pão | K6: 43774 | L6: 1.5
H7: lanche faculdade | K7: 43773 | L7: 3.5
H8: pão | K8: 43778 | L8: 2
H9: batata | K9: 43778 | L9: 9.79
H10: pão | K10: 43779 | L10: 2
H11: pão | K11: 43782 | L11: 1
H12: pão | K12: 43783 | L12: 1
H13: pão | K13: 43788 | L13: 1.5
H14: pão | K14: 43787 | L14: 1.5
H15: cheetos | K15: 43787 | L15: 2
H16: pão | K16: 43789 | L16: 1.5
H17: pão | K17: 43791 | L17: 1.5
H18: pão | K18: 43792 | L18: 2
H19: pão | K19: 43796 | L19: 1
B37: Total | F37: =SUM(F6:F12) -> 7 | H37: Total | L37: =SUM(L6:L36) -> 31.79
B39: Pessoal | H39: Compras casa
B40: Observação | E40: dia | F40: R$ | H40: Observação | K40: dia | L40: R$
B41: emprestar dinheiro a vó | E41: 43770 | F41: 100 | H41: garrafão | K41: 43777 | L41: 8
B42: comprar luva e atadura | E42: 43773 | F42: 160 | H42: frango | K42: 43789 | L42: =9-4 -> 5
B43: reboque | E43: 43779 | F43: 50 | H43: leite integral | K43: 43791 | L43: 3.29
B44: plus | E44: 43780 | F44: 89.9 | H44: ketchup | K44: 43791 | L44: 3.39
B45: azitromicina | E45: 43781 | F45: 22 | H45: garrafão | K45: 43792 | L45: 4
B46: crédito cartão | E46: 43785 | F46: 650 | H46: leite integral | K46: 43796 | L46: 4
B47: shapoo condicionador + netflix | E47: 43785 | F47: 40 | H47: leite integral | K47: 43798 | L47: 4
B48: calça jeans + 2xshort jeans + 2 bermudas | E48: 43786 | F48: 110 | H48: pão hamburguer + hamburguer | K48: 43798 | L48: 11.89
B49: estacionamento via sul | E49: 43786 | F49: 2.6 | H49: caixa de ovo | K49: 43798 | L49: 10
B50: comida para o filme os Parças 2 | E50: 43786 | F50: =25.95/2 -> 12.975
B51: imprimir boleto curio net | E51: 43792 | F51: 0.5
B52: pagar a curio net | E52: 43792 | F52: =72.54-35 -> 37.54
B53: emprestar dinheiro a mãe | E53: 43795 | F53: 8
B64: Total | F64: =SUM(F41:F63) -> 1283.515 | L64: =SUM(L41:L55) -> 53.57
B66: Sherlock | H66: Celular
B67: Observação | E67: dia | F67: R$ | H67: Observação | K67: dia | L67: R$
H68: crédito | K68: 43786 | L68: 54.99
B75: Total | F75: =SUM(F68:F74) -> 0 | H75: Total | L75: =SUM(L68:L74) -> 54.99
B77: Água | H77: Luz
B78: Observação | E78: dia | F78: R$ | H78: Observação | K78: dia | L78: R$
B79: cagece | E79: 43776 | F79: 43.5 | H79: enel | K79: 43776 | L79: 43.5
B86: Total | F86: =SUM(F79:F85) -> 43.5 | H86: Total | L86: =SUM(L79:L85) -> 43.5
B88: Gás | H88: Renda 2 - Trufas
B89: Observação | E89: dia | F89: R$ | H89: Observação | K89: dia | L89: R$
N112: =80-L119 -> 80
B119: Total | F119: =SUM(F90:F96) -> 0 | H119: Total | L119: =SUM(L90:L118) -> 0
B121: Moto
B122: Observação | E122: dia | F122: R$
B123: gasolina | E123: 43779 | F123: 37.63
B124: gasolina | E124: 43780 | F124: 20
B125: cama de ar | E125: 43784 | F125: 30
B126: troca de óleo | E126: 43789 | F126: 22
B127: bastão para olhar o nivel do óleo | E127: 43789 | F127: 10
B128: gasolina | E128: 43798 | F128: 5
B129: gasolina | E129: 43799 | F129: 35
B139: Total | F139: =SUM(F123:F138) -> 159.63

Sheet Gastos Dezembro
B1: Dezembro
B4: Entretenimento | H4: Comida
B5: Observação | E5: dia | F5: R$ | H5: Observação | K5: dia | L5: R$
H6: pão | K6: 43802 | L6: 1.5
H7: pão | K7: 43803 | L7: 1.5
H8: tortuguita | K8: 43802 | L8: 1
H9: tortuguita | K9: 43801 | L9: 1
H10: pão | K10: 43804 | L10: 1
H11: pão | K11: 43805 | L11: 1
H12: pão | K12: 43807 | L12: 1
H13: água de coco | K13: 43807 | L13: 3
H14: jantar bia | K14: 43808 | L14: 8.3
H15: pão | K15: 43810 | L15: 1.5
H16: jantar com a Bia | K16: 43813 | L16: 12
H17: pão | K17: 43815 | L17: 1
... H20: pão | K20: 43818 | L20: 1
H21: lanche para o filme | K21: 43818 | L21: =12 -> 12
H22: jantar pizza | K22: 43821 | L22: 15
H23: jantar subway | K23: 43828 | L23: =10.3+13.9 -> 24.2
B37: Total | F37: =SUM(F6:F12) -> 0 | H37: Total | L37: =SUM(L6:L36) -> 88.5
B39: Pessoal | H39: Compras casa
B40: Observação | E40: dia | F40: R$ | H40: Observação | K40: dia | L40: R$
B41: emprestar dinheiro a mãe | E41: 43804 | F41: 60 | H41: leite | K41: 43801 | L41: 3.29
B42: travesseiro | E42: 43806 | F42: 20 | H42: 2 kg de arroz | K42: 43801 | L42: 5.29
B43: presente amigo secreto | E43: 43807 | F43: 49.9 | H43: banana | K43: 43810 | L43: 5
B44: park games iguatemi | E44: 43808 | F44: 7.75 | H44: farinha dágua | K44: 43811 | L44: 2.75
B45: plus | E45: 43808 | F45: 89.9 | H45: 2x sardinha 88 | K45: 43811 | L45: 4.48
B46: leite condesado | E46: 43811 | F46: 2.98 | H46: sacola das compras | K46: 43811 | L46: 0.05
B47: flocos de chocolate | E47: 43811 | F47: 6.99 | H47: 2x garrafão | K47: 43815 | L47: 8
B48: forma de brigadeiro | E48: 43811 | F48: 1 | H48: frango | K48: 43816 | L48: 5
B49: bolo de chocolate para a Plus | E49: 43812 | F49: 13 | H49: bolo + cream craker | K49: 43819 | L49: 10.3
B50: leite condesado | E50: 43815 | F50: 2.98 | H50: 2x garrafão | K50: 43823 | L50: 8
B51: 2x leite condesado | E51: 43816 | F51: =2*2.98 -> 5.96 | H51: banana+maracuja | K51: 43826 | L51: 10.45
B52: forma de brigadeiro | E52: 43816 | F52: 1
B53: comprar revista de pintar | E53: 43816 | F53: 2
B54: ingresso star wars 9 | E54: 43818 | F54: 14
B55: estacionamento via sul | E55: 43818 | F55: 2.95
B56: netflix | E56: 43818 | F56: 23
B57: uber para casa | E57: 43820 | F57: 6.3
B58: chinela | E58: 43826 | F58: 19.9
B59: remédio | E59: 43827 | F59: 25
B60: estacionamento iguatemi | E60: 43828 | F60: 2.5
B64: Total | F64: =SUM(F41:F63) -> 357.11 | L64: =SUM(L41:L55) -> 62.61
B66: Sherlock | H66: Celular
B67: Observação | E67: dia | F67: R$ | H67: Observação | K67: dia | L67: R$
B68: ração | E68: 43800 | F68: 20
M74: =94/3 -> 31.333333
B75: Total | F75: =SUM(F68:F74) -> 20 | H75: Total | L75: =SUM(L68:L74) -> 0
B77: Água | H77: Luz
B78: Observação | E78: dia | F78: R$ | H78: Observação | K78: dia | L78: R$
B79: cagece | E79: 12/121/2019 | F79: 24.9 | H79: enel | K79: 43811 | L79: 52.39
B86: Total | F86: =SUM(F79:F85) -> 24.9 | H86: Total | L86: =SUM(L79:L85) -> 52.39
B88: Gás | H88: Renda 2 - Trufas
B89: Observação | E89: dia | F89: R$ | H89: Observação | K89: dia | L89: R$
B90: gas de cozinha | E90: 43819 | F90: 36
B119: Total | F119: =SUM(F90:F96) -> 36 | H119: Total | L119: =SUM(L90:L118) -> 0
B121: Moto
B122: Observação | E122: dia | F122: R$
B123: gasolina | E123: 43806 | F123: 15
B124: pisca da moto | E124: 43808 | F124: 8
B125: capa | E125: 43809 | F125: 30
B126: gasolina | E126: 43812 | F126: 20
B127: troca de óleo | E127: 43818 | F127: 22
B128: gasolina | E128: 43828 | F128: 10
B139: Total | F139: =SUM(F123:F138) -> 105
